{
    "rootDir": "src",
    "files": [
        "manifest",
        "source/**/*.*",
        "images/**/*.*",
        "components/**/*.*",
        {
            "src": "../src-demo-app/manifest",
            "dest": ""
        },
        {
            "src": "../src-demo-app/**/*.*",
            "dest": ""
        },
        "!**/*.spec.bs"
    ],
    "stagingDir": "build",
    "createPackage": false,
    "retainStagingDir": true,
    "autoImportComponentScript": true,
    "sourceMap": true,
    "ignoreErrorCodes": [1107],
    "plugins": [
        "@rokucommunity/bslint"
    ]
}
